CHANGELOG.md
LICENSE
MANIFEST.in
README.md
setup.cfg
setup.py
pip_clients_logging/__init__.py
pip_clients_logging.egg-info/PKG-INFO
pip_clients_logging.egg-info/SOURCES.txt
pip_clients_logging.egg-info/dependency_links.txt
pip_clients_logging.egg-info/requires.txt
pip_clients_logging.egg-info/top_level.txt
pip_clients_logging.egg-info/zip-safe
pip_clients_logging/build/LoggingFactory.py
pip_clients_logging/build/__init__.py
pip_clients_logging/log/AbstractLogger.py
pip_clients_logging/log/DirectLogger.py
pip_clients_logging/log/HttpLogger.py
pip_clients_logging/log/__init__.py
pip_clients_logging/version1/ILoggingClientV1.py
pip_clients_logging/version1/LogMessageV1.py
pip_clients_logging/version1/LoggingDirectClientV1.py
pip_clients_logging/version1/LoggingHttpClientV1.py
pip_clients_logging/version1/LoggingNullClientV1.py
pip_clients_logging/version1/__init__.py